package_creation_tutorial/__init__.py
package_creation_tutorial/string_ops.py
fatma_package_creation_tutorial-0.1.1.dist-info/METADATA
fatma_package_creation_tutorial-0.1.1.dist-info/WHEEL
fatma_package_creation_tutorial-0.1.1.dist-info/RECORD
